carabas2tools/__init__.py
carabas2tools/carabas2.py
carabas2tools/image_info.py
carabas2tools/mission_info.py
carabas2tools-1.0.0.dist-info/METADATA
carabas2tools-1.0.0.dist-info/WHEEL
carabas2tools-1.0.0.dist-info/top_level.txt
carabas2tools-1.0.0.dist-info/RECORD
