Metadata-Version: 2.4
Name: carabas2tools
Version: 1.0.0
Summary: A collection of tools to work with CARABAS-II dataset
Home-page: https://github.com/gabrielluizep/carabas2tools
Author: Gabriel Luiz Espindola Pedro
Author-email: gabrielluizep.glep@gmail.com
Requires-Dist: numpy
Requires-Dist: scipy
Requires-Dist: pandas
Dynamic: author
Dynamic: author-email
Dynamic: home-page
Dynamic: requires-dist
Dynamic: summary
